{
  "_class": "document",
  "assets": {
    "_class": "assetCollection",
    "colorAssets": [
    ],
    "colors": [
    ],
    "do_objectID": "E2A733BF-2C50-40B7-A6A9-86B1E07E5354",
    "exportPresets": [
    ],
    "gradientAssets": [
    ],
    "gradients": [
    ],
    "imageCollection": {
      "_class": "imageCollection",
      "images": {
      }
    },
    "images": [
    ]
  },
  "colorSpace": 0,
  "do_objectID": "3AEF3FD9-6400-4B52-9FB4-B0E58D09D31F",
  "fontReferences": [
    {
      "_class": "fontReference",
      "do_objectID": "1241412E-4E22-4E86-83C5-ECFB9572DA4D",
      "fontFamilyName": "Montserrat",
      "fontFileName": "Montserrat-Medium.ttf",
      "options": 0,
      "postscriptNames": [
        "Montserrat-Medium"
      ]
    },
    {
      "_class": "fontReference",
      "do_objectID": "14EA158B-FF65-4319-9AE3-302AAAB0DBD0",
      "fontFamilyName": "Sarabun",
      "fontFileName": "Sarabun-SemiBold.ttf",
      "options": 2,
      "postscriptNames": [
        "Sarabun-SemiBold"
      ]
    },
    {
      "_class": "fontReference",
      "do_objectID": "1FB684FE-FB5A-4D5F-9840-363400113F05",
      "fontFamilyName": "Sarabun",
      "fontFileName": "Sarabun-Bold.ttf",
      "options": 2,
      "postscriptNames": [
        "Sarabun-Bold"
      ]
    },
    {
      "_class": "fontReference",
      "do_objectID": "29893F9E-5A30-4460-8954-2E394E64C146",
      "fontFamilyName": "Sarabun",
      "fontFileName": "Sarabun-ExtraBoldItalic.ttf",
      "options": 0,
      "postscriptNames": [
        "Sarabun-ExtraBoldItalic"
      ]
    },
    {
      "_class": "fontReference",
      "do_objectID": "32065F69-B2E5-4AD1-9156-520EECC02AB0",
      "fontFamilyName": "Montserrat",
      "fontFileName": "Montserrat-Bold.ttf",
      "options": 0,
      "postscriptNames": [
        "Montserrat-Bold"
      ]
    },
    {
      "_class": "fontReference",
      "do_objectID": "3BF14EEC-879C-434D-BA0F-C121FE5F3E23",
      "fontFamilyName": "Sarabun",
      "fontFileName": "Sarabun-SemiBoldItalic.ttf",
      "options": 0,
      "postscriptNames": [
        "Sarabun-SemiBoldItalic"
      ]
    },
    {
      "_class": "fontReference",
      "do_objectID": "4CE5C4D7-26B0-45B1-9364-ADF507CD36FF",
      "fontFamilyName": "Sarabun",
      "fontFileName": "Sarabun-LightItalic.ttf",
      "options": 0,
      "postscriptNames": [
        "Sarabun-LightItalic"
      ]
    },
    {
      "_class": "fontReference",
      "do_objectID": "4EF50FED-21E5-436F-8548-3CBE2BA4D02A",
      "fontFamilyName": "Sarabun",
      "fontFileName": "Sarabun-Medium.ttf",
      "options": 2,
      "postscriptNames": [
        "Sarabun-Medium"
      ]
    },
    {
      "_class": "fontReference",
      "do_objectID": "97C6143F-930E-4CDB-9E51-587DFD1024F5",
      "fontFamilyName": "Sarabun",
      "fontFileName": "Sarabun-BoldItalic.ttf",
      "options": 0,
      "postscriptNames": [
        "Sarabun-BoldItalic"
      ]
    },
    {
      "_class": "fontReference",
      "do_objectID": "9C394AF5-918C-493B-A592-CF5FB0FC66BD",
      "fontFamilyName": "Sarabun",
      "fontFileName": "Sarabun-ExtraLight.ttf",
      "options": 0,
      "postscriptNames": [
        "Sarabun-ExtraLight"
      ]
    },
    {
      "_class": "fontReference",
      "do_objectID": "9D8FB11B-62F2-4A87-BCFF-191EEA47A32E",
      "fontFamilyName": "Sarabun",
      "fontFileName": "Sarabun-ThinItalic.ttf",
      "options": 0,
      "postscriptNames": [
        "Sarabun-ThinItalic"
      ]
    },
    {
      "_class": "fontReference",
      "do_objectID": "A2908512-D2A8-42D7-BDBD-68FB6AA05E13",
      "fontFamilyName": "Sarabun",
      "fontFileName": "Sarabun-ExtraLightItalic.ttf",
      "options": 0,
      "postscriptNames": [
        "Sarabun-ExtraLightItalic"
      ]
    },
    {
      "_class": "fontReference",
      "do_objectID": "A4DF9067-BBB8-4184-93FA-3783285E7CAC",
      "fontFamilyName": "Sarabun",
      "fontFileName": "Sarabun-ExtraBold.ttf",
      "options": 2,
      "postscriptNames": [
        "Sarabun-ExtraBold"
      ]
    },
    {
      "_class": "fontReference",
      "do_objectID": "B0D5CE2D-8209-44AD-8528-5235C8A26DB0",
      "fontFamilyName": "Sarabun",
      "fontFileName": "Sarabun-Light.ttf",
      "options": 0,
      "postscriptNames": [
        "Sarabun-Light"
      ]
    },
    {
      "_class": "fontReference",
      "do_objectID": "B378A821-76A8-4E00-A5D8-C8130D2145D5",
      "fontFamilyName": "Sarabun",
      "fontFileName": "Sarabun-Italic.ttf",
      "options": 0,
      "postscriptNames": [
        "Sarabun-Italic"
      ]
    },
    {
      "_class": "fontReference",
      "do_objectID": "BF47C733-DFDE-4AA9-9552-5E8B8668C94E",
      "fontFamilyName": "Sarabun",
      "fontFileName": "Sarabun-Thin.ttf",
      "options": 0,
      "postscriptNames": [
        "Sarabun-Thin"
      ]
    },
    {
      "_class": "fontReference",
      "do_objectID": "D61713A6-8507-48A3-9B2D-3F1707BF0593",
      "fontFamilyName": "Sarabun",
      "fontFileName": "Sarabun-MediumItalic.ttf",
      "options": 0,
      "postscriptNames": [
        "Sarabun-MediumItalic"
      ]
    },
    {
      "_class": "fontReference",
      "do_objectID": "F00BA4AE-BC21-4BBE-8BAE-668A50D6002C",
      "fontFamilyName": "Sarabun",
      "fontFileName": "Sarabun-Regular.ttf",
      "options": 2,
      "postscriptNames": [
        "Sarabun-Regular"
      ]
    },
    {
      "_class": "fontReference",
      "do_objectID": "FF3716AA-A8FB-4561-AC5B-8533135A7A5A",
      "fontFamilyName": "Montserrat",
      "fontFileName": "Montserrat-SemiBold.ttf",
      "options": 2,
      "postscriptNames": [
        "Montserrat-SemiBold"
      ]
    }
  ],
  "foreignLayerStyles": [
  ],
  "foreignSwatches": [
  ],
  "foreignSymbols": [
  ],
  "foreignTextStyles": [
  ],
  "layerSymbols": {
    "_class": "symbolContainer",
    "objects": [
    ]
  },
  "meta": {
    "appVersion": "68.1",
    "build": 102560,
    "version": 131
  },
  "pages": [
    "Web",
    "APP",
    "Symbols"
  ],
  "sharedSwatches": {
    "_class": "swatchContainer",
    "objects": [
    ]
  },
  "userInfo": {
    "com.invision.dsm": {
      "libraryMetadata": {
        "5e0f8cfb8673a510135e3fd9": {
          "name": "Design System Mijo",
          "styleguideId": "5e0f8cfb8673a510135e3fd9",
          "updatedOn": "2020-07-22 23:04:57 +0000"
        },
        "null": {
          "layerStylesMap": {
          },
          "symbolsMap": {
          },
          "textStylesMap": {
          }
        },
        "sketchLibrariesData": {
          "layerStylesMap": {
          },
          "symbolsMap": {
          },
          "textStylesMap": {
          }
        }
      }
    },
    "com.invisionlabs.sync": {
      "metadata": "{\"hasSynced\":0,\"hasProjectIdChanged\":0,\"projectId\":0,\"publicLink\":\"\",\"resolution\":2,\"syncAll\":1}"
    }
  }
}